forgecloud/__init__.py
forgecloud/config.py
forgecloud/forge.py
forgecloud/post_process.py
forgecloud/pre_process.py
forgecloud/print_test.py
forgecloud/run_app.py
forgecloud/utils.py
forgecloud/view_app.py
forgecloud/cloudfunctions/__init__.py
forgecloud/cloudfunctions/firestore_save.py
forgecloud-0.0.21.dist-info/METADATA
forgecloud-0.0.21.dist-info/WHEEL
forgecloud-0.0.21.dist-info/top_level.txt
forgecloud-0.0.21.dist-info/RECORD
